pysimultanui/__about__.py
pysimultanui/__init__.py
pysimultanui/cli.py
pysimultanui/config.py
pysimultanui/main_ui.py
pysimultanui/router.py
pysimultanui/app/__init__.py
pysimultanui/app/auth.py
pysimultanui/app/home.py
pysimultanui/app/login.py
pysimultanui/app/logs.py
pysimultanui/app/menue.py
pysimultanui/app/project.py
pysimultanui/app/theme.py
pysimultanui/core/__init__.py
pysimultanui/core/edit_dialog.py
pysimultanui/core/geo_associations.py
pysimultanui/core/logging.py
pysimultanui/core/mappers.py
pysimultanui/core/method_mapper.py
pysimultanui/core/navigation.py
pysimultanui/core/patch_default_models.py
pysimultanui/core/project_manager.py
pysimultanui/core/tools.py
pysimultanui/core/ui_log.py
pysimultanui/core/user.py
pysimultanui/core/freecad_utils/__init__.py
pysimultanui/core/freecad_utils/tools.py
pysimultanui/fastapi_app/__init__.py
pysimultanui/geometry_3d/__init__.py
pysimultanui/geometry_3d/geometry_3d.py
pysimultanui/geometry_3d/mesh_scene.js
pysimultanui/geometry_3d/objects3d.py
pysimultanui/geometry_3d/scene.py
pysimultanui/geometry_3d/three_simgeo.py
pysimultanui/geometry_3d/three_views.py
pysimultanui/geometry_3d/tools.py
pysimultanui/views/__init__.py
pysimultanui/views/argument_dialog.py
pysimultanui/views/array_view.py
pysimultanui/views/component_detail_base_view.py
pysimultanui/views/detail_views.py
pysimultanui/views/grid_view.py
pysimultanui/views/numpy_view.py
pysimultanui/views/pandas_df_view.py
pysimultanui/views/parameter_view.py
pysimultanui/views/type_view.py
pysimultanui/views/type_view_manager.py
pysimultanui/views/utils.py
pysimultanui/views/view_manager.py
pysimultanui/views/asset_view/__init__.py
pysimultanui/views/asset_view/asset_manager.py
pysimultanui/views/asset_view/asset_view.py
pysimultanui/views/component_dict_view/__init__.py
pysimultanui/views/component_dict_view/component_dict_manager.py
pysimultanui/views/component_dict_view/component_dict_view.py
pysimultanui/views/component_list_view/__init__.py
pysimultanui-2.2.1.dist-info/METADATA
pysimultanui-2.2.1.dist-info/WHEEL
pysimultanui-2.2.1.dist-info/entry_points.txt
pysimultanui-2.2.1.dist-info/licenses/LICENSE.txt
pysimultanui-2.2.1.dist-info/RECORD
